hcl2tf/__init__.py
hcl2tf/compact.py
hcl2tf/utils.py
hcl2tf-0.1.1.dist-info/METADATA
hcl2tf-0.1.1.dist-info/WHEEL
hcl2tf-0.1.1.dist-info/top_level.txt
hcl2tf-0.1.1.dist-info/RECORD
